idcardreader_package/__init__.py
idcardreader_package/idcardreader.py
desko_identy_chrom_card_reader-0.0.1.dist-info/LICENSE
desko_identy_chrom_card_reader-0.0.1.dist-info/METADATA
desko_identy_chrom_card_reader-0.0.1.dist-info/WHEEL
desko_identy_chrom_card_reader-0.0.1.dist-info/top_level.txt
desko_identy_chrom_card_reader-0.0.1.dist-info/RECORD
