Metadata-Version: 2.1
Name: desko-identy-chrom-card-reader
Version: 0.0.1
Summary: Python driver for DESKO IDenty chrom
Home-page: https://github.com/matusmol/id_card_reader
Author: Matus Mol
Author-email: matusmol93@gmail.com
License: UNKNOWN
Project-URL: Bug Tracker, https://github.com/matusmol/id_card_reader/issues
Platform: UNKNOWN
Classifier: Programming Language :: Python :: 3
Classifier: License :: OSI Approved :: MIT License
Classifier: Operating System :: OS Independent
Requires-Python: >=3.7
License-File: LICENSE
